{
  "job_id": "job_20251225_105447_f419220a",
  "responses": [
    {
      "timestamp": "2025-12-25T10:54:47.756268",
      "claim_id": "c1",
      "response": {
        "miner_id": "error",
        "claim_id": "c1",
        "verdict": "unverifiable",
        "rationale": "System Error: name 'json' is not defined",
        "evidence_links": [],
        "embedding": null,
        "scores": {
          "accuracy": 0.0,
          "omission_risk": 0.0,
          "evidence_quality": 0.0,
          "governance_relevance": 0.0,
          "composite": 0.0
        },
        "cortensor_raw": {
          "error": "name 'json' is not defined"
        }
      }
    },
    {
      "timestamp": "2025-12-25T10:54:47.884723",
      "claim_id": "c2",
      "response": {
        "miner_id": "error",
        "claim_id": "c2",
        "verdict": "unverifiable",
        "rationale": "System Error: name 'json' is not defined",
        "evidence_links": [],
        "embedding": null,
        "scores": {
          "accuracy": 0.0,
          "omission_risk": 0.0,
          "evidence_quality": 0.0,
          "governance_relevance": 0.0,
          "composite": 0.0
        },
        "cortensor_raw": {
          "error": "name 'json' is not defined"
        }
      }
    }
  ]
}